mkdocs_multirepo_plugin/__init__.py
mkdocs_multirepo_plugin/plugin.py
mkdocs_multirepo_plugin/scripts/mv_docs_up.sh
mkdocs_multirepo_plugin/scripts/sparse_clone.sh
mkdocs_multirepo_plugin/scripts/sparse_clone_old.sh
mkdocs_multirepo_plugin/structure.py
mkdocs_multirepo_plugin/util.py
mkdocs_multirepo_plugin-0.8.2.data/scripts/sparse_clone.sh
mkdocs_multirepo_plugin-0.8.2.data/scripts/sparse_clone_old.sh
mkdocs_multirepo_plugin-0.8.2.data/scripts/mv_docs_up.sh
mkdocs_multirepo_plugin-0.8.2.dist-info/LICENSE
mkdocs_multirepo_plugin-0.8.2.dist-info/METADATA
mkdocs_multirepo_plugin-0.8.2.dist-info/WHEEL
mkdocs_multirepo_plugin-0.8.2.dist-info/entry_points.txt
mkdocs_multirepo_plugin-0.8.2.dist-info/RECORD
