Metadata-Version: 2.1
Name: mkdocs-multirepo-plugin
Version: 0.8.2
Summary: Build documentation in multiple repos into one site.
Home-page: https://pypi.org/project/mkdocs-multirepo-plugin/
License: MIT
Keywords: mkdocs,docs,documentation
Author: jdoiro3
Author-email: josephdoiron1234@yahoo.com
Classifier: Development Status :: 3 - Alpha
Classifier: Intended Audience :: Developers
Classifier: License :: OSI Approved :: MIT License
Classifier: Operating System :: MacOS
Classifier: Operating System :: Microsoft :: Windows
Classifier: Operating System :: POSIX :: Linux
Classifier: Programming Language :: Python
Classifier: Programming Language :: Python :: 2
Classifier: Programming Language :: Python :: 2.7
Classifier: Programming Language :: Python :: 3
Classifier: Programming Language :: Python :: 3.4
Classifier: Programming Language :: Python :: 3.5
Classifier: Programming Language :: Python :: 3.6
Classifier: Programming Language :: Python :: 3.7
Classifier: Programming Language :: Python :: 3.8
Classifier: Programming Language :: Python :: 3.9
Classifier: Programming Language :: Python :: 3.10
Classifier: Programming Language :: Python :: 3.11
Classifier: Programming Language :: Python :: 3.12
Classifier: Topic :: Documentation
Requires-Dist: asyncio ; python_full_version <= "3.8.0"
Requires-Dist: dacite (>=1.8.0,<2.0.0) ; python_version >= "3.6"
Requires-Dist: mkdocs (>=1.0.4) ; python_version >= "3.6"
Requires-Dist: python-slugify ; python_version >= "2.7" and python_version < "2.8" or python_full_version >= "3.6.0"
Requires-Dist: typing-inspect (>=0.8.0,<0.9.0) ; python_version >= "3.6"
Project-URL: Repository, https://github.com/jdoiro3/mkdocs-multirepo-plugin
